butterrand/__init__.py
butterrand/core.py
butterrand-0.1.2.dist-info/licenses/LICENSE
butterrand-0.1.2.dist-info/METADATA
butterrand-0.1.2.dist-info/WHEEL
butterrand-0.1.2.dist-info/top_level.txt
butterrand-0.1.2.dist-info/RECORD
