Metadata-Version: 2.4
Name: butterrand
Version: 0.1.2
Summary: Random number generator based on butterfly effect and chaotic maps
Author: Bùi Phong Phú
Author-email: omerasutvail@gmail.com
License: MIT
Classifier: Programming Language :: Python :: 3
Classifier: License :: OSI Approved :: MIT License
Classifier: Operating System :: OS Independent
Requires-Python: >=3.7
License-File: LICENSE
Dynamic: author
Dynamic: author-email
Dynamic: classifier
Dynamic: description
Dynamic: description-content-type
Dynamic: license
Dynamic: license-file
Dynamic: requires-python
Dynamic: summary
